<?xml version="1.0" encoding="UTF-8" standalone="yes"?>
<LUT_config>
	<enhance major_version="2"/>
	<enhance flag_bit_no="0"/>
	<enhance version="1907161251"/>
	<reg_table mode="auto">
		<param r="0" g="0" b="0"/>
		<param r="0" g="0" b="128"/>
		<param r="0" g="0" b="257"/>
		<param r="0" g="0" b="385"/>
		<param r="0" g="0" b="514"/>
		<param r="0" g="0" b="642"/>
		<param r="0" g="0" b="770"/>
		<param r="0" g="0" b="899"/>
		<param r="0" g="0" b="1023"/>
		<param r="0" g="128" b="0"/>
		<param r="0" g="128" b="128"/>
		<param r="0" g="128" b="257"/>
		<param r="0" g="128" b="385"/>
		<param r="0" g="128" b="514"/>
		<param r="0" g="128" b="642"/>
		<param r="0" g="128" b="770"/>
		<param r="0" g="128" b="899"/>
		<param r="0" g="128" b="1023"/>
		<param r="0" g="257" b="0"/>
		<param r="0" g="257" b="128"/>
		<param r="0" g="257" b="257"/>
		<param r="0" g="257" b="385"/>
		<param r="0" g="257" b="514"/>
		<param r="0" g="257" b="642"/>
		<param r="0" g="257" b="770"/>
		<param r="0" g="257" b="899"/>
		<param r="0" g="257" b="1023"/>
		<param r="0" g="385" b="0"/>
		<param r="0" g="385" b="128"/>
		<param r="0" g="385" b="257"/>
		<param r="0" g="385" b="385"/>
		<param r="0" g="385" b="514"/>
		<param r="0" g="385" b="642"/>
		<param r="0" g="385" b="770"/>
		<param r="0" g="385" b="899"/>
		<param r="0" g="385" b="1023"/>
		<param r="0" g="514" b="0"/>
		<param r="0" g="514" b="128"/>
		<param r="0" g="514" b="257"/>
		<param r="0" g="514" b="385"/>
		<param r="0" g="514" b="514"/>
		<param r="0" g="514" b="642"/>
		<param r="0" g="514" b="770"/>
		<param r="0" g="514" b="899"/>
		<param r="0" g="514" b="1023"/>
		<param r="0" g="642" b="0"/>
		<param r="0" g="642" b="128"/>
		<param r="0" g="642" b="257"/>
		<param r="0" g="642" b="385"/>
		<param r="0" g="642" b="514"/>
		<param r="0" g="642" b="642"/>
		<param r="0" g="642" b="770"/>
		<param r="0" g="642" b="899"/>
		<param r="0" g="642" b="1023"/>
		<param r="0" g="770" b="0"/>
		<param r="0" g="770" b="128"/>
		<param r="0" g="770" b="257"/>
		<param r="0" g="770" b="385"/>
		<param r="0" g="770" b="514"/>
		<param r="0" g="770" b="642"/>
		<param r="0" g="770" b="770"/>
		<param r="0" g="770" b="899"/>
		<param r="0" g="770" b="1023"/>
		<param r="0" g="899" b="0"/>
		<param r="0" g="899" b="128"/>
		<param r="0" g="899" b="257"/>
		<param r="0" g="899" b="385"/>
		<param r="0" g="899" b="514"/>
		<param r="0" g="899" b="642"/>
		<param r="0" g="899" b="770"/>
		<param r="0" g="899" b="899"/>
		<param r="0" g="899" b="1023"/>
		<param r="0" g="1023" b="0"/>
		<param r="0" g="1023" b="128"/>
		<param r="0" g="1023" b="257"/>
		<param r="0" g="1023" b="385"/>
		<param r="0" g="1023" b="514"/>
		<param r="0" g="1023" b="642"/>
		<param r="0" g="1023" b="770"/>
		<param r="0" g="1023" b="899"/>
		<param r="0" g="1023" b="1023"/>
		<param r="128" g="0" b="0"/>
		<param r="128" g="0" b="128"/>
		<param r="128" g="0" b="257"/>
		<param r="128" g="0" b="385"/>
		<param r="128" g="0" b="514"/>
		<param r="128" g="0" b="642"/>
		<param r="128" g="0" b="770"/>
		<param r="128" g="0" b="899"/>
		<param r="128" g="0" b="1023"/>
		<param r="128" g="128" b="0"/>
		<param r="128" g="128" b="128"/>
		<param r="128" g="128" b="257"/>
		<param r="128" g="128" b="385"/>
		<param r="128" g="128" b="514"/>
		<param r="128" g="128" b="642"/>
		<param r="128" g="128" b="770"/>
		<param r="128" g="128" b="899"/>
		<param r="128" g="128" b="1023"/>
		<param r="128" g="257" b="0"/>
		<param r="128" g="257" b="128"/>
		<param r="128" g="257" b="257"/>
		<param r="128" g="257" b="385"/>
		<param r="128" g="257" b="514"/>
		<param r="128" g="257" b="642"/>
		<param r="128" g="257" b="770"/>
		<param r="128" g="257" b="899"/>
		<param r="128" g="257" b="1023"/>
		<param r="128" g="385" b="0"/>
		<param r="128" g="385" b="128"/>
		<param r="128" g="385" b="257"/>
		<param r="128" g="385" b="385"/>
		<param r="128" g="385" b="514"/>
		<param r="128" g="385" b="642"/>
		<param r="128" g="385" b="770"/>
		<param r="128" g="385" b="899"/>
		<param r="128" g="385" b="1023"/>
		<param r="128" g="514" b="0"/>
		<param r="128" g="514" b="128"/>
		<param r="128" g="514" b="257"/>
		<param r="128" g="514" b="385"/>
		<param r="128" g="514" b="514"/>
		<param r="128" g="514" b="642"/>
		<param r="128" g="514" b="770"/>
		<param r="128" g="514" b="899"/>
		<param r="128" g="514" b="1023"/>
		<param r="128" g="642" b="0"/>
		<param r="128" g="642" b="128"/>
		<param r="128" g="642" b="257"/>
		<param r="128" g="642" b="385"/>
		<param r="128" g="642" b="514"/>
		<param r="128" g="642" b="642"/>
		<param r="128" g="642" b="770"/>
		<param r="128" g="642" b="899"/>
		<param r="128" g="642" b="1023"/>
		<param r="128" g="770" b="0"/>
		<param r="128" g="770" b="128"/>
		<param r="128" g="770" b="257"/>
		<param r="128" g="770" b="385"/>
		<param r="128" g="770" b="514"/>
		<param r="128" g="770" b="642"/>
		<param r="128" g="770" b="770"/>
		<param r="128" g="770" b="899"/>
		<param r="128" g="770" b="1023"/>
		<param r="128" g="899" b="0"/>
		<param r="128" g="899" b="128"/>
		<param r="128" g="899" b="257"/>
		<param r="128" g="899" b="385"/>
		<param r="128" g="899" b="514"/>
		<param r="128" g="899" b="642"/>
		<param r="128" g="899" b="770"/>
		<param r="128" g="899" b="899"/>
		<param r="128" g="899" b="1023"/>
		<param r="128" g="1023" b="0"/>
		<param r="128" g="1023" b="128"/>
		<param r="128" g="1023" b="257"/>
		<param r="128" g="1023" b="385"/>
		<param r="128" g="1023" b="514"/>
		<param r="128" g="1023" b="642"/>
		<param r="128" g="1023" b="770"/>
		<param r="128" g="1023" b="899"/>
		<param r="128" g="1023" b="1023"/>
		<param r="257" g="0" b="0"/>
		<param r="257" g="0" b="128"/>
		<param r="257" g="0" b="257"/>
		<param r="257" g="0" b="385"/>
		<param r="257" g="0" b="514"/>
		<param r="257" g="0" b="642"/>
		<param r="257" g="0" b="770"/>
		<param r="257" g="0" b="899"/>
		<param r="257" g="0" b="1023"/>
		<param r="257" g="128" b="0"/>
		<param r="257" g="128" b="128"/>
		<param r="257" g="128" b="257"/>
		<param r="257" g="128" b="385"/>
		<param r="257" g="128" b="514"/>
		<param r="257" g="128" b="642"/>
		<param r="257" g="128" b="770"/>
		<param r="257" g="128" b="899"/>
		<param r="257" g="128" b="1023"/>
		<param r="257" g="257" b="0"/>
		<param r="257" g="257" b="128"/>
		<param r="257" g="257" b="257"/>
		<param r="257" g="257" b="385"/>
		<param r="257" g="257" b="514"/>
		<param r="257" g="257" b="642"/>
		<param r="257" g="257" b="770"/>
		<param r="257" g="257" b="899"/>
		<param r="257" g="257" b="1023"/>
		<param r="257" g="385" b="0"/>
		<param r="257" g="385" b="128"/>
		<param r="257" g="385" b="257"/>
		<param r="257" g="385" b="385"/>
		<param r="257" g="385" b="514"/>
		<param r="257" g="385" b="642"/>
		<param r="257" g="385" b="770"/>
		<param r="257" g="385" b="899"/>
		<param r="257" g="385" b="1023"/>
		<param r="257" g="514" b="0"/>
		<param r="257" g="514" b="128"/>
		<param r="257" g="514" b="257"/>
		<param r="257" g="514" b="385"/>
		<param r="257" g="514" b="514"/>
		<param r="257" g="514" b="642"/>
		<param r="257" g="514" b="770"/>
		<param r="257" g="514" b="899"/>
		<param r="257" g="514" b="1023"/>
		<param r="257" g="642" b="0"/>
		<param r="257" g="642" b="128"/>
		<param r="257" g="642" b="257"/>
		<param r="257" g="642" b="385"/>
		<param r="257" g="642" b="514"/>
		<param r="257" g="642" b="642"/>
		<param r="257" g="642" b="770"/>
		<param r="257" g="642" b="899"/>
		<param r="257" g="642" b="1023"/>
		<param r="257" g="770" b="0"/>
		<param r="257" g="770" b="128"/>
		<param r="257" g="770" b="257"/>
		<param r="257" g="770" b="385"/>
		<param r="257" g="770" b="514"/>
		<param r="257" g="770" b="642"/>
		<param r="257" g="770" b="770"/>
		<param r="257" g="770" b="899"/>
		<param r="257" g="770" b="1023"/>
		<param r="257" g="899" b="0"/>
		<param r="257" g="899" b="128"/>
		<param r="257" g="899" b="257"/>
		<param r="257" g="899" b="385"/>
		<param r="257" g="899" b="514"/>
		<param r="257" g="899" b="642"/>
		<param r="257" g="899" b="770"/>
		<param r="257" g="899" b="899"/>
		<param r="257" g="899" b="1023"/>
		<param r="257" g="1023" b="0"/>
		<param r="257" g="1023" b="128"/>
		<param r="257" g="1023" b="257"/>
		<param r="257" g="1023" b="385"/>
		<param r="257" g="1023" b="514"/>
		<param r="257" g="1023" b="642"/>
		<param r="257" g="1023" b="770"/>
		<param r="257" g="1023" b="899"/>
		<param r="257" g="1023" b="1023"/>
		<param r="385" g="0" b="0"/>
		<param r="385" g="0" b="128"/>
		<param r="385" g="0" b="257"/>
		<param r="385" g="0" b="385"/>
		<param r="385" g="0" b="514"/>
		<param r="385" g="0" b="642"/>
		<param r="385" g="0" b="770"/>
		<param r="385" g="0" b="899"/>
		<param r="385" g="0" b="1023"/>
		<param r="385" g="128" b="0"/>
		<param r="385" g="128" b="128"/>
		<param r="385" g="128" b="257"/>
		<param r="385" g="128" b="385"/>
		<param r="385" g="128" b="514"/>
		<param r="385" g="128" b="642"/>
		<param r="385" g="128" b="770"/>
		<param r="385" g="128" b="899"/>
		<param r="385" g="128" b="1023"/>
		<param r="385" g="257" b="0"/>
		<param r="385" g="257" b="128"/>
		<param r="385" g="257" b="257"/>
		<param r="385" g="257" b="385"/>
		<param r="385" g="257" b="514"/>
		<param r="385" g="257" b="642"/>
		<param r="385" g="257" b="770"/>
		<param r="385" g="257" b="899"/>
		<param r="385" g="257" b="1023"/>
		<param r="385" g="385" b="0"/>
		<param r="385" g="385" b="128"/>
		<param r="385" g="385" b="257"/>
		<param r="385" g="385" b="385"/>
		<param r="385" g="385" b="514"/>
		<param r="385" g="385" b="642"/>
		<param r="385" g="385" b="770"/>
		<param r="385" g="385" b="899"/>
		<param r="385" g="385" b="1023"/>
		<param r="385" g="514" b="0"/>
		<param r="385" g="514" b="128"/>
		<param r="385" g="514" b="257"/>
		<param r="385" g="514" b="385"/>
		<param r="385" g="514" b="514"/>
		<param r="385" g="514" b="642"/>
		<param r="385" g="514" b="770"/>
		<param r="385" g="514" b="899"/>
		<param r="385" g="514" b="1023"/>
		<param r="385" g="642" b="0"/>
		<param r="385" g="642" b="128"/>
		<param r="385" g="642" b="257"/>
		<param r="385" g="642" b="385"/>
		<param r="385" g="642" b="514"/>
		<param r="385" g="642" b="642"/>
		<param r="385" g="642" b="770"/>
		<param r="385" g="642" b="899"/>
		<param r="385" g="642" b="1023"/>
		<param r="385" g="770" b="0"/>
		<param r="385" g="770" b="128"/>
		<param r="385" g="770" b="257"/>
		<param r="385" g="770" b="385"/>
		<param r="385" g="770" b="514"/>
		<param r="385" g="770" b="642"/>
		<param r="385" g="770" b="770"/>
		<param r="385" g="770" b="899"/>
		<param r="385" g="770" b="1023"/>
		<param r="385" g="899" b="0"/>
		<param r="385" g="899" b="128"/>
		<param r="385" g="899" b="257"/>
		<param r="385" g="899" b="385"/>
		<param r="385" g="899" b="514"/>
		<param r="385" g="899" b="642"/>
		<param r="385" g="899" b="770"/>
		<param r="385" g="899" b="899"/>
		<param r="385" g="899" b="1023"/>
		<param r="385" g="1023" b="0"/>
		<param r="385" g="1023" b="128"/>
		<param r="385" g="1023" b="257"/>
		<param r="385" g="1023" b="385"/>
		<param r="385" g="1023" b="514"/>
		<param r="385" g="1023" b="642"/>
		<param r="385" g="1023" b="770"/>
		<param r="385" g="1023" b="899"/>
		<param r="385" g="1023" b="1023"/>
		<param r="514" g="0" b="0"/>
		<param r="514" g="0" b="128"/>
		<param r="514" g="0" b="257"/>
		<param r="514" g="0" b="385"/>
		<param r="514" g="0" b="514"/>
		<param r="514" g="0" b="642"/>
		<param r="514" g="0" b="770"/>
		<param r="514" g="0" b="899"/>
		<param r="514" g="0" b="1023"/>
		<param r="514" g="128" b="0"/>
		<param r="514" g="128" b="128"/>
		<param r="514" g="128" b="257"/>
		<param r="514" g="128" b="385"/>
		<param r="514" g="128" b="514"/>
		<param r="514" g="128" b="642"/>
		<param r="514" g="128" b="770"/>
		<param r="514" g="128" b="899"/>
		<param r="514" g="128" b="1023"/>
		<param r="514" g="257" b="0"/>
		<param r="514" g="257" b="128"/>
		<param r="514" g="257" b="257"/>
		<param r="514" g="257" b="385"/>
		<param r="514" g="257" b="514"/>
		<param r="514" g="257" b="642"/>
		<param r="514" g="257" b="770"/>
		<param r="514" g="257" b="899"/>
		<param r="514" g="257" b="1023"/>
		<param r="514" g="385" b="0"/>
		<param r="514" g="385" b="128"/>
		<param r="514" g="385" b="257"/>
		<param r="514" g="385" b="385"/>
		<param r="514" g="385" b="514"/>
		<param r="514" g="385" b="642"/>
		<param r="514" g="385" b="770"/>
		<param r="514" g="385" b="899"/>
		<param r="514" g="385" b="1023"/>
		<param r="514" g="514" b="0"/>
		<param r="514" g="514" b="128"/>
		<param r="514" g="514" b="257"/>
		<param r="514" g="514" b="385"/>
		<param r="514" g="514" b="514"/>
		<param r="514" g="514" b="642"/>
		<param r="514" g="514" b="770"/>
		<param r="514" g="514" b="899"/>
		<param r="514" g="514" b="1023"/>
		<param r="514" g="642" b="0"/>
		<param r="514" g="642" b="128"/>
		<param r="514" g="642" b="257"/>
		<param r="514" g="642" b="385"/>
		<param r="514" g="642" b="514"/>
		<param r="514" g="642" b="642"/>
		<param r="514" g="642" b="770"/>
		<param r="514" g="642" b="899"/>
		<param r="514" g="642" b="1023"/>
		<param r="514" g="770" b="0"/>
		<param r="514" g="770" b="128"/>
		<param r="514" g="770" b="257"/>
		<param r="514" g="770" b="385"/>
		<param r="514" g="770" b="514"/>
		<param r="514" g="770" b="642"/>
		<param r="514" g="770" b="770"/>
		<param r="514" g="770" b="899"/>
		<param r="514" g="770" b="1023"/>
		<param r="514" g="899" b="0"/>
		<param r="514" g="899" b="128"/>
		<param r="514" g="899" b="257"/>
		<param r="514" g="899" b="385"/>
		<param r="514" g="899" b="514"/>
		<param r="514" g="899" b="642"/>
		<param r="514" g="899" b="770"/>
		<param r="514" g="899" b="899"/>
		<param r="514" g="899" b="1023"/>
		<param r="514" g="1023" b="0"/>
		<param r="514" g="1023" b="128"/>
		<param r="514" g="1023" b="257"/>
		<param r="514" g="1023" b="385"/>
		<param r="514" g="1023" b="514"/>
		<param r="514" g="1023" b="642"/>
		<param r="514" g="1023" b="770"/>
		<param r="514" g="1023" b="899"/>
		<param r="514" g="1023" b="1023"/>
		<param r="642" g="0" b="0"/>
		<param r="642" g="0" b="128"/>
		<param r="642" g="0" b="257"/>
		<param r="642" g="0" b="385"/>
		<param r="642" g="0" b="514"/>
		<param r="642" g="0" b="642"/>
		<param r="642" g="0" b="770"/>
		<param r="642" g="0" b="899"/>
		<param r="642" g="0" b="1023"/>
		<param r="642" g="128" b="0"/>
		<param r="642" g="128" b="128"/>
		<param r="642" g="128" b="257"/>
		<param r="642" g="128" b="385"/>
		<param r="642" g="128" b="514"/>
		<param r="642" g="128" b="642"/>
		<param r="642" g="128" b="770"/>
		<param r="642" g="128" b="899"/>
		<param r="642" g="128" b="1023"/>
		<param r="642" g="257" b="0"/>
		<param r="642" g="257" b="128"/>
		<param r="642" g="257" b="257"/>
		<param r="642" g="257" b="385"/>
		<param r="642" g="257" b="514"/>
		<param r="642" g="257" b="642"/>
		<param r="642" g="257" b="770"/>
		<param r="642" g="257" b="899"/>
		<param r="642" g="257" b="1023"/>
		<param r="642" g="385" b="0"/>
		<param r="642" g="385" b="128"/>
		<param r="642" g="385" b="257"/>
		<param r="642" g="385" b="385"/>
		<param r="642" g="385" b="514"/>
		<param r="642" g="385" b="642"/>
		<param r="642" g="385" b="770"/>
		<param r="642" g="385" b="899"/>
		<param r="642" g="385" b="1023"/>
		<param r="642" g="514" b="0"/>
		<param r="642" g="514" b="128"/>
		<param r="642" g="514" b="257"/>
		<param r="642" g="514" b="385"/>
		<param r="642" g="514" b="514"/>
		<param r="642" g="514" b="642"/>
		<param r="642" g="514" b="770"/>
		<param r="642" g="514" b="899"/>
		<param r="642" g="514" b="1023"/>
		<param r="642" g="642" b="0"/>
		<param r="642" g="642" b="128"/>
		<param r="642" g="642" b="257"/>
		<param r="642" g="642" b="385"/>
		<param r="642" g="642" b="514"/>
		<param r="642" g="642" b="642"/>
		<param r="642" g="642" b="770"/>
		<param r="642" g="642" b="899"/>
		<param r="642" g="642" b="1023"/>
		<param r="642" g="770" b="0"/>
		<param r="642" g="770" b="128"/>
		<param r="642" g="770" b="257"/>
		<param r="642" g="770" b="385"/>
		<param r="642" g="770" b="514"/>
		<param r="642" g="770" b="642"/>
		<param r="642" g="770" b="770"/>
		<param r="642" g="770" b="899"/>
		<param r="642" g="770" b="1023"/>
		<param r="642" g="899" b="0"/>
		<param r="642" g="899" b="128"/>
		<param r="642" g="899" b="257"/>
		<param r="642" g="899" b="385"/>
		<param r="642" g="899" b="514"/>
		<param r="642" g="899" b="642"/>
		<param r="642" g="899" b="770"/>
		<param r="642" g="899" b="899"/>
		<param r="642" g="899" b="1023"/>
		<param r="642" g="1023" b="0"/>
		<param r="642" g="1023" b="128"/>
		<param r="642" g="1023" b="257"/>
		<param r="642" g="1023" b="385"/>
		<param r="642" g="1023" b="514"/>
		<param r="642" g="1023" b="642"/>
		<param r="642" g="1023" b="770"/>
		<param r="642" g="1023" b="899"/>
		<param r="642" g="1023" b="1023"/>
		<param r="770" g="0" b="0"/>
		<param r="770" g="0" b="128"/>
		<param r="770" g="0" b="257"/>
		<param r="770" g="0" b="385"/>
		<param r="770" g="0" b="514"/>
		<param r="770" g="0" b="642"/>
		<param r="770" g="0" b="770"/>
		<param r="770" g="0" b="899"/>
		<param r="770" g="0" b="1023"/>
		<param r="770" g="128" b="0"/>
		<param r="770" g="128" b="128"/>
		<param r="770" g="128" b="257"/>
		<param r="770" g="128" b="385"/>
		<param r="770" g="128" b="514"/>
		<param r="770" g="128" b="642"/>
		<param r="770" g="128" b="770"/>
		<param r="770" g="128" b="899"/>
		<param r="770" g="128" b="1023"/>
		<param r="770" g="257" b="0"/>
		<param r="770" g="257" b="128"/>
		<param r="770" g="257" b="257"/>
		<param r="770" g="257" b="385"/>
		<param r="770" g="257" b="514"/>
		<param r="770" g="257" b="642"/>
		<param r="770" g="257" b="770"/>
		<param r="770" g="257" b="899"/>
		<param r="770" g="257" b="1023"/>
		<param r="770" g="385" b="0"/>
		<param r="770" g="385" b="128"/>
		<param r="770" g="385" b="257"/>
		<param r="770" g="385" b="385"/>
		<param r="770" g="385" b="514"/>
		<param r="770" g="385" b="642"/>
		<param r="770" g="385" b="770"/>
		<param r="770" g="385" b="899"/>
		<param r="770" g="385" b="1023"/>
		<param r="770" g="514" b="0"/>
		<param r="770" g="514" b="128"/>
		<param r="770" g="514" b="257"/>
		<param r="770" g="514" b="385"/>
		<param r="770" g="514" b="514"/>
		<param r="770" g="514" b="642"/>
		<param r="770" g="514" b="770"/>
		<param r="770" g="514" b="899"/>
		<param r="770" g="514" b="1023"/>
		<param r="770" g="642" b="0"/>
		<param r="770" g="642" b="128"/>
		<param r="770" g="642" b="257"/>
		<param r="770" g="642" b="385"/>
		<param r="770" g="642" b="514"/>
		<param r="770" g="642" b="642"/>
		<param r="770" g="642" b="770"/>
		<param r="770" g="642" b="899"/>
		<param r="770" g="642" b="1023"/>
		<param r="770" g="770" b="0"/>
		<param r="770" g="770" b="128"/>
		<param r="770" g="770" b="257"/>
		<param r="770" g="770" b="385"/>
		<param r="770" g="770" b="514"/>
		<param r="770" g="770" b="642"/>
		<param r="770" g="770" b="770"/>
		<param r="770" g="770" b="899"/>
		<param r="770" g="770" b="1023"/>
		<param r="770" g="899" b="0"/>
		<param r="770" g="899" b="128"/>
		<param r="770" g="899" b="257"/>
		<param r="770" g="899" b="385"/>
		<param r="770" g="899" b="514"/>
		<param r="770" g="899" b="642"/>
		<param r="770" g="899" b="770"/>
		<param r="770" g="899" b="899"/>
		<param r="770" g="899" b="1023"/>
		<param r="770" g="1023" b="0"/>
		<param r="770" g="1023" b="128"/>
		<param r="770" g="1023" b="257"/>
		<param r="770" g="1023" b="385"/>
		<param r="770" g="1023" b="514"/>
		<param r="770" g="1023" b="642"/>
		<param r="770" g="1023" b="770"/>
		<param r="770" g="1023" b="899"/>
		<param r="770" g="1023" b="1023"/>
		<param r="899" g="0" b="0"/>
		<param r="899" g="0" b="128"/>
		<param r="899" g="0" b="257"/>
		<param r="899" g="0" b="385"/>
		<param r="899" g="0" b="514"/>
		<param r="899" g="0" b="642"/>
		<param r="899" g="0" b="770"/>
		<param r="899" g="0" b="899"/>
		<param r="899" g="0" b="1023"/>
		<param r="899" g="128" b="0"/>
		<param r="899" g="128" b="128"/>
		<param r="899" g="128" b="257"/>
		<param r="899" g="128" b="385"/>
		<param r="899" g="128" b="514"/>
		<param r="899" g="128" b="642"/>
		<param r="899" g="128" b="770"/>
		<param r="899" g="128" b="899"/>
		<param r="899" g="128" b="1023"/>
		<param r="899" g="257" b="0"/>
		<param r="899" g="257" b="128"/>
		<param r="899" g="257" b="257"/>
		<param r="899" g="257" b="385"/>
		<param r="899" g="257" b="514"/>
		<param r="899" g="257" b="642"/>
		<param r="899" g="257" b="770"/>
		<param r="899" g="257" b="899"/>
		<param r="899" g="257" b="1023"/>
		<param r="899" g="385" b="0"/>
		<param r="899" g="385" b="128"/>
		<param r="899" g="385" b="257"/>
		<param r="899" g="385" b="385"/>
		<param r="899" g="385" b="514"/>
		<param r="899" g="385" b="642"/>
		<param r="899" g="385" b="770"/>
		<param r="899" g="385" b="899"/>
		<param r="899" g="385" b="1023"/>
		<param r="899" g="514" b="0"/>
		<param r="899" g="514" b="128"/>
		<param r="899" g="514" b="257"/>
		<param r="899" g="514" b="385"/>
		<param r="899" g="514" b="514"/>
		<param r="899" g="514" b="642"/>
		<param r="899" g="514" b="770"/>
		<param r="899" g="514" b="899"/>
		<param r="899" g="514" b="1023"/>
		<param r="899" g="642" b="0"/>
		<param r="899" g="642" b="128"/>
		<param r="899" g="642" b="257"/>
		<param r="899" g="642" b="385"/>
		<param r="899" g="642" b="514"/>
		<param r="899" g="642" b="642"/>
		<param r="899" g="642" b="770"/>
		<param r="899" g="642" b="899"/>
		<param r="899" g="642" b="1023"/>
		<param r="899" g="770" b="0"/>
		<param r="899" g="770" b="128"/>
		<param r="899" g="770" b="257"/>
		<param r="899" g="770" b="385"/>
		<param r="899" g="770" b="514"/>
		<param r="899" g="770" b="642"/>
		<param r="899" g="770" b="770"/>
		<param r="899" g="770" b="899"/>
		<param r="899" g="770" b="1023"/>
		<param r="899" g="899" b="0"/>
		<param r="899" g="899" b="128"/>
		<param r="899" g="899" b="257"/>
		<param r="899" g="899" b="385"/>
		<param r="899" g="899" b="514"/>
		<param r="899" g="899" b="642"/>
		<param r="899" g="899" b="770"/>
		<param r="899" g="899" b="899"/>
		<param r="899" g="899" b="1023"/>
		<param r="899" g="1023" b="0"/>
		<param r="899" g="1023" b="128"/>
		<param r="899" g="1023" b="257"/>
		<param r="899" g="1023" b="385"/>
		<param r="899" g="1023" b="514"/>
		<param r="899" g="1023" b="642"/>
		<param r="899" g="1023" b="770"/>
		<param r="899" g="1023" b="899"/>
		<param r="899" g="1023" b="1023"/>
		<param r="1023" g="0" b="0"/>
		<param r="1023" g="0" b="128"/>
		<param r="1023" g="0" b="257"/>
		<param r="1023" g="0" b="385"/>
		<param r="1023" g="0" b="514"/>
		<param r="1023" g="0" b="642"/>
		<param r="1023" g="0" b="770"/>
		<param r="1023" g="0" b="899"/>
		<param r="1023" g="0" b="1023"/>
		<param r="1023" g="128" b="0"/>
		<param r="1023" g="128" b="128"/>
		<param r="1023" g="128" b="257"/>
		<param r="1023" g="128" b="385"/>
		<param r="1023" g="128" b="514"/>
		<param r="1023" g="128" b="642"/>
		<param r="1023" g="128" b="770"/>
		<param r="1023" g="128" b="899"/>
		<param r="1023" g="128" b="1023"/>
		<param r="1023" g="257" b="0"/>
		<param r="1023" g="257" b="128"/>
		<param r="1023" g="257" b="257"/>
		<param r="1023" g="257" b="385"/>
		<param r="1023" g="257" b="514"/>
		<param r="1023" g="257" b="642"/>
		<param r="1023" g="257" b="770"/>
		<param r="1023" g="257" b="899"/>
		<param r="1023" g="257" b="1023"/>
		<param r="1023" g="385" b="0"/>
		<param r="1023" g="385" b="128"/>
		<param r="1023" g="385" b="257"/>
		<param r="1023" g="385" b="385"/>
		<param r="1023" g="385" b="514"/>
		<param r="1023" g="385" b="642"/>
		<param r="1023" g="385" b="770"/>
		<param r="1023" g="385" b="899"/>
		<param r="1023" g="385" b="1023"/>
		<param r="1023" g="514" b="0"/>
		<param r="1023" g="514" b="128"/>
		<param r="1023" g="514" b="257"/>
		<param r="1023" g="514" b="385"/>
		<param r="1023" g="514" b="514"/>
		<param r="1023" g="514" b="642"/>
		<param r="1023" g="514" b="770"/>
		<param r="1023" g="514" b="899"/>
		<param r="1023" g="514" b="1023"/>
		<param r="1023" g="642" b="0"/>
		<param r="1023" g="642" b="128"/>
		<param r="1023" g="642" b="257"/>
		<param r="1023" g="642" b="385"/>
		<param r="1023" g="642" b="514"/>
		<param r="1023" g="642" b="642"/>
		<param r="1023" g="642" b="770"/>
		<param r="1023" g="642" b="899"/>
		<param r="1023" g="642" b="1023"/>
		<param r="1023" g="770" b="0"/>
		<param r="1023" g="770" b="128"/>
		<param r="1023" g="770" b="257"/>
		<param r="1023" g="770" b="385"/>
		<param r="1023" g="770" b="514"/>
		<param r="1023" g="770" b="642"/>
		<param r="1023" g="770" b="770"/>
		<param r="1023" g="770" b="899"/>
		<param r="1023" g="770" b="1023"/>
		<param r="1023" g="899" b="0"/>
		<param r="1023" g="899" b="128"/>
		<param r="1023" g="899" b="257"/>
		<param r="1023" g="899" b="385"/>
		<param r="1023" g="899" b="514"/>
		<param r="1023" g="899" b="642"/>
		<param r="1023" g="899" b="770"/>
		<param r="1023" g="899" b="899"/>
		<param r="1023" g="899" b="1023"/>
		<param r="1023" g="1023" b="0"/>
		<param r="1023" g="1023" b="128"/>
		<param r="1023" g="1023" b="257"/>
		<param r="1023" g="1023" b="385"/>
		<param r="1023" g="1023" b="514"/>
		<param r="1023" g="1023" b="642"/>
		<param r="1023" g="1023" b="770"/>
		<param r="1023" g="1023" b="899"/>
		<param r="1023" g="1023" b="1023"/>
	</reg_table>
	<reg_table mode="enhance">
		<param r="0" g="0" b="0"/>
		<param r="0" g="27" b="103"/>
		<param r="1" g="7" b="225"/>
		<param r="6" g="26" b="353"/>
		<param r="13" g="52" b="456"/>
		<param r="21" g="98" b="582"/>
		<param r="14" g="131" b="700"/>
		<param r="15" g="184" b="816"/>
		<param r="23" g="211" b="948"/>
		<param r="2" g="92" b="0"/>
		<param r="0" g="95" b="84"/>
		<param r="0" g="94" b="224"/>
		<param r="10" g="115" b="349"/>
		<param r="15" g="136" b="464"/>
		<param r="9" g="170" b="585"/>
		<param r="84" g="205" b="705"/>
		<param r="10" g="213" b="817"/>
		<param r="17" g="231" b="944"/>
		<param r="28" g="235" b="4"/>
		<param r="18" g="245" b="73"/>
		<param r="13" g="248" b="229"/>
		<param r="0" g="252" b="346"/>
		<param r="0" g="263" b="468"/>
		<param r="0" g="270" b="577"/>
		<param r="0" g="285" b="701"/>
		<param r="0" g="295" b="816"/>
		<param r="0" g="313" b="944"/>
		<param r="112" g="364" b="0"/>
		<param r="42" g="369" b="60"/>
		<param r="29" g="370" b="224"/>
		<param r="25" g="374" b="348"/>
		<param r="5" g="378" b="467"/>
		<param r="13" g="385" b="587"/>
		<param r="1" g="403" b="728"/>
		<param r="44" g="405" b="818"/>
		<param r="11" g="412" b="954"/>
		<param r="102" g="477" b="0"/>
		<param r="75" g="496" b="56"/>
		<param r="56" g="494" b="200"/>
		<param r="63" g="496" b="345"/>
		<param r="67" g="500" b="465"/>
		<param r="34" g="505" b="585"/>
		<param r="45" g="511" b="709"/>
		<param r="2" g="517" b="833"/>
		<param r="2" g="526" b="960"/>
		<param r="190" g="610" b="5"/>
		<param r="120" g="613" b="22"/>
		<param r="116" g="614" b="213"/>
		<param r="96" g="616" b="339"/>
		<param r="97" g="619" b="462"/>
		<param r="88" g="623" b="583"/>
		<param r="83" g="628" b="707"/>
		<param r="68" g="635" b="831"/>
		<param r="51" g="641" b="958"/>
		<param r="245" g="735" b="0"/>
		<param r="107" g="818" b="82"/>
		<param r="178" g="743" b="204"/>
		<param r="169" g="744" b="336"/>
		<param r="91" g="748" b="444"/>
		<param r="157" g="750" b="580"/>
		<param r="110" g="754" b="711"/>
		<param r="121" g="759" b="829"/>
		<param r="127" g="764" b="957"/>
		<param r="268" g="845" b="9"/>
		<param r="229" g="859" b="3"/>
		<param r="220" g="868" b="188"/>
		<param r="211" g="869" b="326"/>
		<param r="214" g="871" b="454"/>
		<param r="205" g="873" b="576"/>
		<param r="204" g="877" b="702"/>
		<param r="185" g="881" b="826"/>
		<param r="175" g="884" b="954"/>
		<param r="300" g="994" b="13"/>
		<param r="267" g="994" b="9"/>
		<param r="244" g="990" b="171"/>
		<param r="238" g="991" b="316"/>
		<param r="238" g="993" b="446"/>
		<param r="235" g="995" b="571"/>
		<param r="229" g="998" b="697"/>
		<param r="228" g="1001" b="823"/>
		<param r="220" g="1004" b="952"/>
		<param r="86" g="5" b="0"/>
		<param r="63" g="0" b="78"/>
		<param r="75" g="3" b="233"/>
		<param r="80" g="30" b="354"/>
		<param r="68" g="78" b="471"/>
		<param r="44" g="100" b="589"/>
		<param r="38" g="138" b="713"/>
		<param r="25" g="174" b="836"/>
		<param r="7" g="212" b="962"/>
		<param r="82" g="91" b="0"/>
		<param r="80" g="86" b="75"/>
		<param r="89" g="99" b="231"/>
		<param r="84" g="115" b="353"/>
		<param r="68" g="136" b="471"/>
		<param r="50" g="162" b="589"/>
		<param r="44" g="187" b="713"/>
		<param r="28" g="217" b="836"/>
		<param r="5" g="236" b="962"/>
		<param r="89" g="241" b="0"/>
		<param r="104" g="243" b="73"/>
		<param r="88" g="247" b="228"/>
		<param r="80" g="252" b="350"/>
		<param r="84" g="263" b="469"/>
		<param r="50" g="271" b="587"/>
		<param r="52" g="285" b="712"/>
		<param r="23" g="295" b="835"/>
		<param r="13" g="311" b="961"/>
		<param r="192" g="409" b="0"/>
		<param r="125" g="368" b="59"/>
		<param r="107" g="370" b="224"/>
		<param r="110" g="373" b="348"/>
		<param r="88" g="378" b="467"/>
		<param r="90" g="385" b="586"/>
		<param r="75" g="392" b="710"/>
		<param r="62" g="402" b="834"/>
		<param r="47" g="413" b="960"/>
		<param r="168" g="483" b="0"/>
		<param r="145" g="492" b="37"/>
		<param r="138" g="493" b="218"/>
		<param r="136" g="495" b="345"/>
		<param r="115" g="500" b="469"/>
		<param r="112" g="504" b="584"/>
		<param r="97" g="511" b="710"/>
		<param r="77" g="518" b="833"/>
		<param r="79" g="526" b="959"/>
		<param r="212" g="610" b="3"/>
		<param r="188" g="613" b="21"/>
		<param r="183" g="614" b="213"/>
		<param r="163" g="616" b="339"/>
		<param r="161" g="619" b="462"/>
		<param r="159" g="623" b="583"/>
		<param r="146" g="628" b="707"/>
		<param r="135" g="634" b="831"/>
		<param r="123" g="640" b="958"/>
		<param r="263" g="735" b="0"/>
		<param r="216" g="742" b="1"/>
		<param r="217" g="743" b="204"/>
		<param r="212" g="744" b="336"/>
		<param r="188" g="747" b="456"/>
		<param r="206" g="750" b="580"/>
		<param r="118" g="755" b="707"/>
		<param r="178" g="758" b="829"/>
		<param r="105" g="764" b="957"/>
		<param r="286" g="846" b="9"/>
		<param r="252" g="859" b="4"/>
		<param r="246" g="868" b="187"/>
		<param r="237" g="869" b="326"/>
		<param r="241" g="871" b="454"/>
		<param r="230" g="874" b="576"/>
		<param r="230" g="877" b="702"/>
		<param r="223" g="881" b="826"/>
		<param r="216" g="885" b="954"/>
		<param r="270" g="1023" b="30"/>
		<param r="289" g="994" b="10"/>
		<param r="266" g="990" b="170"/>
		<param r="260" g="991" b="316"/>
		<param r="259" g="993" b="446"/>
		<param r="257" g="995" b="571"/>
		<param r="251" g="998" b="697"/>
		<param r="249" g="1001" b="823"/>
		<param r="242" g="1004" b="951"/>
		<param r="269" g="10" b="6"/>
		<param r="255" g="6" b="74"/>
		<param r="248" g="27" b="232"/>
		<param r="239" g="52" b="353"/>
		<param r="243" g="77" b="471"/>
		<param r="233" g="103" b="589"/>
		<param r="231" g="140" b="712"/>
		<param r="228" g="176" b="835"/>
		<param r="219" g="213" b="961"/>
		<param r="268" g="86" b="0"/>
		<param r="253" g="98" b="73"/>
		<param r="249" g="104" b="230"/>
		<param r="240" g="120" b="352"/>
		<param r="243" g="134" b="470"/>
		<param r="234" g="162" b="588"/>
		<param r="233" g="189" b="712"/>
		<param r="229" g="218" b="835"/>
		<param r="219" g="237" b="961"/>
		<param r="253" g="239" b="0"/>
		<param r="259" g="245" b="71"/>
		<param r="237" g="248" b="225"/>
		<param r="244" g="255" b="350"/>
		<param r="250" g="264" b="468"/>
		<param r="234" g="271" b="587"/>
		<param r="235" g="285" b="711"/>
		<param r="227" g="294" b="834"/>
		<param r="221" g="311" b="960"/>
		<param r="274" g="364" b="0"/>
		<param r="259" g="367" b="58"/>
		<param r="255" g="369" b="223"/>
		<param r="250" g="373" b="348"/>
		<param r="251" g="376" b="467"/>
		<param r="245" g="384" b="586"/>
		<param r="242" g="391" b="710"/>
		<param r="238" g="401" b="833"/>
		<param r="231" g="412" b="960"/>
		<param r="256" g="487" b="0"/>
		<param r="277" g="492" b="47"/>
		<param r="273" g="493" b="218"/>
		<param r="264" g="496" b="344"/>
		<param r="267" g="499" b="465"/>
		<param r="253" g="504" b="584"/>
		<param r="257" g="511" b="709"/>
		<param r="243" g="517" b="832"/>
		<param r="240" g="525" b="959"/>
		<param r="294" g="610" b="11"/>
		<param r="280" g="613" b="20"/>
		<param r="278" g="613" b="212"/>
		<param r="271" g="615" b="338"/>
		<param r="274" g="618" b="462"/>
		<param r="268" g="623" b="582"/>
		<param r="268" g="628" b="707"/>
		<param r="261" g="634" b="831"/>
		<param r="255" g="641" b="957"/>
		<param r="279" g="818" b="44"/>
		<param r="281" g="742" b="1"/>
		<param r="301" g="743" b="203"/>
		<param r="298" g="744" b="336"/>
		<param r="293" g="747" b="458"/>
		<param r="289" g="750" b="580"/>
		<param r="288" g="754" b="704"/>
		<param r="276" g="759" b="829"/>
		<param r="276" g="764" b="956"/>
		<param r="363" g="822" b="0"/>
		<param r="320" g="859" b="5"/>
		<param r="317" g="868" b="186"/>
		<param r="313" g="869" b="325"/>
		<param r="308" g="871" b="451"/>
		<param r="307" g="874" b="575"/>
		<param r="308" g="877" b="702"/>
		<param r="298" g="881" b="826"/>
		<param r="295" g="885" b="954"/>
		<param r="375" g="993" b="13"/>
		<param r="324" g="1023" b="34"/>
		<param r="341" g="991" b="169"/>
		<param r="336" g="992" b="316"/>
		<param r="332" g="993" b="446"/>
		<param r="332" g="995" b="571"/>
		<param r="325" g="998" b="697"/>
		<param r="322" g="1002" b="823"/>
		<param r="317" g="1004" b="951"/>
		<param r="384" g="16" b="1"/>
		<param r="382" g="18" b="71"/>
		<param r="377" g="31" b="230"/>
		<param r="377" g="51" b="352"/>
		<param r="370" g="75" b="470"/>
		<param r="373" g="110" b="588"/>
		<param r="366" g="152" b="712"/>
		<param r="359" g="186" b="834"/>
		<param r="359" g="215" b="960"/>
		<param r="462" g="94" b="0"/>
		<param r="382" g="94" b="67"/>
		<param r="378" g="105" b="228"/>
		<param r="378" g="124" b="351"/>
		<param r="371" g="147" b="469"/>
		<param r="375" g="173" b="588"/>
		<param r="367" g="196" b="711"/>
		<param r="360" g="220" b="834"/>
		<param r="359" g="238" b="960"/>
		<param r="368" g="240" b="0"/>
		<param r="381" g="244" b="69"/>
		<param r="378" g="246" b="225"/>
		<param r="377" g="251" b="349"/>
		<param r="373" g="262" b="468"/>
		<param r="375" g="269" b="586"/>
		<param r="368" g="285" b="711"/>
		<param r="359" g="295" b="834"/>
		<param r="361" g="313" b="960"/>
		<param r="392" g="400" b="24"/>
		<param r="392" g="370" b="54"/>
		<param r="385" g="372" b="217"/>
		<param r="377" g="375" b="346"/>
		<param r="379" g="381" b="466"/>
		<param r="383" g="387" b="585"/>
		<param r="373" g="394" b="709"/>
		<param r="369" g="404" b="833"/>
		<param r="367" g="413" b="959"/>
		<param r="372" g="501" b="37"/>
		<param r="392" g="492" b="32"/>
		<param r="389" g="493" b="216"/>
		<param r="386" g="496" b="344"/>
		<param r="380" g="499" b="462"/>
		<param r="385" g="504" b="584"/>
		<param r="379" g="512" b="708"/>
		<param r="372" g="517" b="831"/>
		<param r="374" g="526" b="958"/>
		<param r="415" g="611" b="4"/>
		<param r="407" g="614" b="16"/>
		<param r="404" g="615" b="211"/>
		<param r="397" g="617" b="337"/>
		<param r="396" g="620" b="461"/>
		<param r="396" g="624" b="582"/>
		<param r="391" g="629" b="706"/>
		<param r="388" g="635" b="830"/>
		<param r="383" g="641" b="957"/>
		<param r="442" g="736" b="0"/>
		<param r="417" g="744" b="2"/>
		<param r="414" g="744" b="201"/>
		<param r="410" g="746" b="335"/>
		<param r="404" g="748" b="455"/>
		<param r="408" g="751" b="579"/>
		<param r="370" g="756" b="704"/>
		<param r="401" g="759" b="828"/>
		<param r="383" g="765" b="955"/>
		<param r="447" g="846" b="16"/>
		<param r="429" g="860" b="4"/>
		<param r="430" g="869" b="184"/>
		<param r="425" g="870" b="324"/>
		<param r="426" g="872" b="453"/>
		<param r="421" g="875" b="575"/>
		<param r="420" g="878" b="701"/>
		<param r="418" g="882" b="825"/>
		<param r="412" g="886" b="953"/>
		<param r="489" g="993" b="28"/>
		<param r="464" g="994" b="18"/>
		<param r="442" g="991" b="166"/>
		<param r="438" g="993" b="315"/>
		<param r="438" g="994" b="445"/>
		<param r="436" g="996" b="570"/>
		<param r="433" g="999" b="696"/>
		<param r="432" g="1002" b="822"/>
		<param r="427" g="1005" b="951"/>
		<param r="516" g="48" b="0"/>
		<param r="511" g="38" b="67"/>
		<param r="508" g="50" b="228"/>
		<param r="505" g="74" b="351"/>
		<param r="505" g="100" b="469"/>
		<param r="500" g="125" b="587"/>
		<param r="503" g="155" b="711"/>
		<param r="494" g="195" b="834"/>
		<param r="491" g="220" b="960"/>
		<param r="516" g="101" b="0"/>
		<param r="511" g="115" b="65"/>
		<param r="508" g="121" b="227"/>
		<param r="506" g="135" b="350"/>
		<param r="505" g="150" b="468"/>
		<param r="501" g="178" b="587"/>
		<param r="504" g="202" b="711"/>
		<param r="494" g="224" b="834"/>
		<param r="491" g="244" b="960"/>
		<param r="497" g="246" b="7"/>
		<param r="512" g="248" b="65"/>
		<param r="510" g="251" b="223"/>
		<param r="507" g="258" b="348"/>
		<param r="501" g="263" b="467"/>
		<param r="502" g="278" b="586"/>
		<param r="505" g="291" b="710"/>
		<param r="495" g="303" b="833"/>
		<param r="493" g="318" b="959"/>
		<param r="509" g="371" b="0"/>
		<param r="514" g="370" b="50"/>
		<param r="512" g="371" b="220"/>
		<param r="509" g="375" b="346"/>
		<param r="509" g="379" b="465"/>
		<param r="505" g="387" b="585"/>
		<param r="507" g="394" b="709"/>
		<param r="499" g="406" b="832"/>
		<param r="497" g="416" b="959"/>
		<param r="513" g="486" b="0"/>
		<param r="524" g="495" b="37"/>
		<param r="519" g="496" b="214"/>
		<param r="517" g="499" b="343"/>
		<param r="510" g="502" b="463"/>
		<param r="512" g="508" b="583"/>
		<param r="514" g="514" b="708"/>
		<param r="503" g="521" b="831"/>
		<param r="503" g="529" b="958"/>
		<param r="543" g="612" b="25"/>
		<param r="524" g="615" b="12"/>
		<param r="522" g="615" b="210"/>
		<param r="520" g="617" b="336"/>
		<param r="519" g="620" b="460"/>
		<param r="516" g="625" b="581"/>
		<param r="517" g="629" b="706"/>
		<param r="511" g="637" b="830"/>
		<param r="509" g="642" b="956"/>
		<param r="571" g="818" b="74"/>
		<param r="551" g="764" b="12"/>
		<param r="535" g="745" b="198"/>
		<param r="534" g="747" b="333"/>
		<param r="530" g="749" b="456"/>
		<param r="528" g="752" b="579"/>
		<param r="526" g="756" b="703"/>
		<param r="519" g="761" b="827"/>
		<param r="520" g="766" b="955"/>
		<param r="567" g="853" b="20"/>
		<param r="547" g="861" b="12"/>
		<param r="541" g="870" b="181"/>
		<param r="539" g="871" b="323"/>
		<param r="536" g="873" b="450"/>
		<param r="536" g="875" b="574"/>
		<param r="535" g="879" b="700"/>
		<param r="529" g="883" b="825"/>
		<param r="529" g="886" b="953"/>
		<param r="588" g="1023" b="45"/>
		<param r="587" g="1023" b="55"/>
		<param r="554" g="993" b="162"/>
		<param r="551" g="993" b="313"/>
		<param r="549" g="995" b="444"/>
		<param r="549" g="997" b="570"/>
		<param r="544" g="1000" b="695"/>
		<param r="542" g="1003" b="822"/>
		<param r="541" g="1006" b="950"/>
		<param r="656" g="85" b="0"/>
		<param r="636" g="53" b="62"/>
		<param r="635" g="61" b="226"/>
		<param r="630" g="80" b="349"/>
		<param r="631" g="102" b="468"/>
		<param r="629" g="131" b="587"/>
		<param r="627" g="168" b="710"/>
		<param r="628" g="207" b="833"/>
		<param r="622" g="227" b="959"/>
		<param r="651" g="174" b="0"/>
		<param r="636" g="115" b="60"/>
		<param r="635" g="122" b="225"/>
		<param r="631" g="141" b="348"/>
		<param r="631" g="160" b="467"/>
		<param r="630" g="189" b="586"/>
		<param r="627" g="214" b="710"/>
		<param r="628" g="230" b="833"/>
		<param r="622" g="247" b="959"/>
		<param r="615" g="266" b="0"/>
		<param r="636" g="254" b="60"/>
		<param r="636" g="255" b="222"/>
		<param r="631" g="261" b="346"/>
		<param r="632" g="268" b="466"/>
		<param r="630" g="276" b="585"/>
		<param r="628" g="290" b="709"/>
		<param r="629" g="300" b="832"/>
		<param r="623" g="317" b="959"/>
		<param r="632" g="388" b="15"/>
		<param r="639" g="371" b="44"/>
		<param r="638" g="373" b="218"/>
		<param r="634" g="378" b="344"/>
		<param r="635" g="382" b="464"/>
		<param r="633" g="390" b="584"/>
		<param r="631" g="399" b="708"/>
		<param r="633" g="410" b="832"/>
		<param r="627" g="421" b="958"/>
		<param r="637" g="494" b="0"/>
		<param r="643" g="496" b="30"/>
		<param r="641" g="497" b="213"/>
		<param r="637" g="500" b="341"/>
		<param r="638" g="503" b="462"/>
		<param r="636" g="508" b="582"/>
		<param r="635" g="515" b="707"/>
		<param r="634" g="520" b="830"/>
		<param r="630" g="529" b="957"/>
		<param r="649" g="622" b="12"/>
		<param r="650" g="618" b="6"/>
		<param r="649" g="618" b="207"/>
		<param r="645" g="621" b="335"/>
		<param r="646" g="624" b="459"/>
		<param r="643" g="628" b="580"/>
		<param r="642" g="634" b="705"/>
		<param r="638" g="640" b="830"/>
		<param r="636" g="646" b="956"/>
		<param r="663" g="738" b="0"/>
		<param r="656" g="747" b="5"/>
		<param r="654" g="746" b="195"/>
		<param r="650" g="748" b="332"/>
		<param r="651" g="750" b="455"/>
		<param r="649" g="754" b="578"/>
		<param r="647" g="757" b="703"/>
		<param r="646" g="762" b="827"/>
		<param r="643" g="767" b="954"/>
		<param r="674" g="864" b="25"/>
		<param r="663" g="864" b="16"/>
		<param r="665" g="872" b="176"/>
		<param r="662" g="873" b="322"/>
		<param r="663" g="875" b="451"/>
		<param r="658" g="878" b="573"/>
		<param r="658" g="881" b="700"/>
		<param r="655" g="885" b="824"/>
		<param r="651" g="888" b="952"/>
		<param r="703" g="993" b="36"/>
		<param r="686" g="995" b="25"/>
		<param r="670" g="994" b="157"/>
		<param r="668" g="995" b="312"/>
		<param r="668" g="996" b="443"/>
		<param r="666" g="998" b="569"/>
		<param r="665" g="1001" b="695"/>
		<param r="663" g="1004" b="821"/>
		<param r="659" g="1007" b="950"/>
		<param r="754" g="130" b="0"/>
		<param r="765" g="77" b="51"/>
		<param r="764" g="86" b="222"/>
		<param r="763" g="105" b="347"/>
		<param r="761" g="132" b="466"/>
		<param r="761" g="159" b="585"/>
		<param r="759" g="188" b="709"/>
		<param r="756" g="215" b="832"/>
		<param r="757" g="232" b="958"/>
		<param r="754" g="177" b="0"/>
		<param r="765" g="146" b="51"/>
		<param r="764" g="154" b="221"/>
		<param r="763" g="165" b="346"/>
		<param r="761" g="183" b="466"/>
		<param r="761" g="205" b="585"/>
		<param r="759" g="219" b="709"/>
		<param r="756" g="236" b="832"/>
		<param r="757" g="253" b="958"/>
		<param r="736" g="269" b="0"/>
		<param r="766" g="257" b="43"/>
		<param r="764" g="260" b="218"/>
		<param r="763" g="265" b="345"/>
		<param r="761" g="272" b="464"/>
		<param r="762" g="283" b="584"/>
		<param r="760" g="297" b="708"/>
		<param r="757" g="309" b="831"/>
		<param r="758" g="326" b="958"/>
		<param r="745" g="392" b="0"/>
		<param r="768" g="379" b="33"/>
		<param r="767" g="380" b="215"/>
		<param r="765" g="384" b="342"/>
		<param r="764" g="389" b="463"/>
		<param r="764" g="395" b="583"/>
		<param r="762" g="403" b="707"/>
		<param r="759" g="414" b="831"/>
		<param r="760" g="423" b="957"/>
		<param r="737" g="485" b="0"/>
		<param r="771" g="498" b="15"/>
		<param r="769" g="499" b="209"/>
		<param r="768" g="502" b="340"/>
		<param r="766" g="505" b="459"/>
		<param r="767" g="511" b="581"/>
		<param r="765" g="518" b="706"/>
		<param r="762" g="525" b="829"/>
		<param r="763" g="533" b="956"/>
		<param r="771" g="620" b="0"/>
		<param r="765" g="615" b="1"/>
		<param r="774" g="621" b="204"/>
		<param r="772" g="623" b="333"/>
		<param r="771" g="626" b="458"/>
		<param r="771" g="629" b="579"/>
		<param r="768" g="635" b="704"/>
		<param r="766" g="641" b="828"/>
		<param r="766" g="647" b="955"/>
		<param r="802" g="802" b="85"/>
		<param r="818" g="783" b="12"/>
		<param r="780" g="749" b="191"/>
		<param r="778" g="750" b="323"/>
		<param r="777" g="753" b="454"/>
		<param r="778" g="756" b="577"/>
		<param r="775" g="760" b="702"/>
		<param r="773" g="765" b="826"/>
		<param r="767" g="770" b="953"/>
		<param r="793" g="847" b="58"/>
		<param r="777" g="848" b="26"/>
		<param r="785" g="873" b="172"/>
		<param r="783" g="874" b="320"/>
		<param r="781" g="876" b="447"/>
		<param r="782" g="878" b="572"/>
		<param r="780" g="882" b="699"/>
		<param r="778" g="886" b="823"/>
		<param r="777" g="889" b="951"/>
		<param r="812" g="1023" b="43"/>
		<param r="814" g="1023" b="34"/>
		<param r="795" g="996" b="151"/>
		<param r="792" g="997" b="306"/>
		<param r="792" g="998" b="442"/>
		<param r="791" g="1000" b="567"/>
		<param r="788" g="1003" b="694"/>
		<param r="788" g="1006" b="820"/>
		<param r="785" g="1009" b="949"/>
		<param r="856" g="183" b="0"/>
		<param r="889" g="105" b="44"/>
		<param r="888" g="112" b="218"/>
		<param r="886" g="129" b="344"/>
		<param r="887" g="147" b="464"/>
		<param r="884" g="177" b="584"/>
		<param r="884" g="206" b="708"/>
		<param r="883" g="224" b="831"/>
		<param r="880" g="244" b="957"/>
		<param r="863" g="197" b="0"/>
		<param r="889" g="160" b="42"/>
		<param r="888" g="167" b="218"/>
		<param r="886" g="183" b="343"/>
		<param r="887" g="200" b="463"/>
		<param r="885" g="216" b="583"/>
		<param r="885" g="230" b="707"/>
		<param r="883" g="247" b="831"/>
		<param r="880" g="266" b="957"/>
		<param r="851" g="298" b="0"/>
		<param r="889" g="263" b="39"/>
		<param r="889" g="269" b="215"/>
		<param r="886" g="278" b="342"/>
		<param r="887" g="284" b="463"/>
		<param r="885" g="292" b="582"/>
		<param r="885" g="303" b="707"/>
		<param r="883" g="315" b="830"/>
		<param r="881" g="330" b="957"/>
		<param r="862" g="413" b="12"/>
		<param r="891" g="380" b="24"/>
		<param r="890" g="382" b="212"/>
		<param r="888" g="386" b="339"/>
		<param r="889" g="391" b="461"/>
		<param r="887" g="399" b="581"/>
		<param r="887" g="408" b="706"/>
		<param r="885" g="419" b="829"/>
		<param r="883" g="429" b="956"/>
		<param r="870" g="506" b="0"/>
		<param r="894" g="503" b="8"/>
		<param r="893" g="504" b="206"/>
		<param r="891" g="507" b="337"/>
		<param r="891" g="510" b="459"/>
		<param r="889" g="515" b="580"/>
		<param r="889" g="521" b="704"/>
		<param r="887" g="527" b="828"/>
		<param r="885" g="535" b="955"/>
		<param r="878" g="628" b="24"/>
		<param r="883" g="586" b="2"/>
		<param r="896" g="623" b="198"/>
		<param r="894" g="625" b="330"/>
		<param r="895" g="628" b="456"/>
		<param r="893" g="633" b="577"/>
		<param r="893" g="637" b="703"/>
		<param r="891" g="644" b="827"/>
		<param r="889" g="651" b="954"/>
		<param r="890" g="739" b="0"/>
		<param r="904" g="748" b="8"/>
		<param r="900" g="750" b="185"/>
		<param r="898" g="752" b="327"/>
		<param r="898" g="754" b="452"/>
		<param r="897" g="757" b="575"/>
		<param r="897" g="761" b="700"/>
		<param r="894" g="766" b="825"/>
		<param r="893" g="771" b="952"/>
		<param r="897" g="871" b="26"/>
		<param r="897" g="871" b="17"/>
		<param r="906" g="875" b="165"/>
		<param r="904" g="876" b="317"/>
		<param r="904" g="878" b="447"/>
		<param r="902" g="881" b="571"/>
		<param r="903" g="884" b="697"/>
		<param r="900" g="889" b="822"/>
		<param r="899" g="893" b="950"/>
		<param r="932" g="994" b="42"/>
		<param r="924" g="997" b="35"/>
		<param r="910" g="997" b="143"/>
		<param r="909" g="997" b="307"/>
		<param r="908" g="999" b="440"/>
		<param r="907" g="1001" b="566"/>
		<param r="907" g="1004" b="692"/>
		<param r="905" g="1007" b="819"/>
		<param r="903" g="1010" b="947"/>
		<param r="957" g="240" b="0"/>
		<param r="1008" g="130" b="29"/>
		<param r="1007" g="138" b="213"/>
		<param r="1006" g="156" b="340"/>
		<param r="1005" g="179" b="461"/>
		<param r="1006" g="202" b="581"/>
		<param r="1003" g="217" b="706"/>
		<param r="1004" g="231" b="829"/>
		<param r="1002" g="249" b="956"/>
		<param r="958" g="255" b="0"/>
		<param r="1008" g="191" b="29"/>
		<param r="1008" g="197" b="213"/>
		<param r="1006" g="207" b="340"/>
		<param r="1005" g="215" b="461"/>
		<param r="1006" g="224" b="581"/>
		<param r="1003" g="238" b="706"/>
		<param r="1004" g="251" b="829"/>
		<param r="1002" g="268" b="956"/>
		<param r="937" g="331" b="0"/>
		<param r="1008" g="270" b="22"/>
		<param r="1008" g="272" b="210"/>
		<param r="1006" g="278" b="339"/>
		<param r="1006" g="284" b="459"/>
		<param r="1006" g="294" b="581"/>
		<param r="1004" g="307" b="705"/>
		<param r="1004" g="318" b="829"/>
		<param r="1003" g="335" b="955"/>
		<param r="969" g="422" b="0"/>
		<param r="1010" g="389" b="10"/>
		<param r="1010" g="391" b="207"/>
		<param r="1008" g="396" b="336"/>
		<param r="1007" g="400" b="458"/>
		<param r="1008" g="407" b="579"/>
		<param r="1006" g="414" b="704"/>
		<param r="1006" g="423" b="828"/>
		<param r="1004" g="432" b="955"/>
		<param r="940" g="490" b="0"/>
		<param r="1010" g="486" b="0"/>
		<param r="1011" g="503" b="201"/>
		<param r="1009" g="507" b="334"/>
		<param r="1009" g="509" b="455"/>
		<param r="1009" g="515" b="578"/>
		<param r="1007" g="522" b="703"/>
		<param r="1007" g="528" b="826"/>
		<param r="1006" g="537" b="954"/>
		<param r="995" g="633" b="0"/>
		<param r="994" g="504" b="0"/>
		<param r="1015" g="627" b="190"/>
		<param r="1012" g="629" b="327"/>
		<param r="1012" g="632" b="454"/>
		<param r="1012" g="635" b="575"/>
		<param r="1010" g="640" b="701"/>
		<param r="1011" g="646" b="825"/>
		<param r="1008" g="652" b="952"/>
		<param r="1007" g="802" b="112"/>
		<param r="1007" g="802" b="130"/>
		<param r="1017" g="751" b="179"/>
		<param r="1015" g="753" b="323"/>
		<param r="1015" g="755" b="448"/>
		<param r="1015" g="759" b="573"/>
		<param r="1014" g="763" b="698"/>
		<param r="1014" g="767" b="823"/>
		<param r="1012" g="773" b="951"/>
		<param r="1023" g="863" b="74"/>
		<param r="1003" g="851" b="34"/>
		<param r="1021" g="876" b="157"/>
		<param r="1019" g="878" b="314"/>
		<param r="1019" g="879" b="443"/>
		<param r="1018" g="882" b="569"/>
		<param r="1017" g="886" b="696"/>
		<param r="1018" g="889" b="820"/>
		<param r="1015" g="893" b="949"/>
		<param r="1017" g="1017" b="66"/>
		<param r="1019" g="1019" b="59"/>
		<param r="1023" g="1000" b="73"/>
		<param r="1023" g="1000" b="284"/>
		<param r="1022" g="1002" b="428"/>
		<param r="1022" g="1004" b="564"/>
		<param r="1023" g="1007" b="690"/>
		<param r="1023" g="1010" b="818"/>
		<param r="1021" g="1013" b="946"/>
	</reg_table>
	<reg_table mode="standard">
		<param r="0" g="0" b="0"/>
		<param r="0" g="24" b="93"/>
		<param r="0" g="12" b="221"/>
		<param r="0" g="25" b="335"/>
		<param r="0" g="62" b="436"/>
		<param r="0" g="100" b="549"/>
		<param r="0" g="116" b="660"/>
		<param r="0" g="178" b="814"/>
		<param r="0" g="206" b="898"/>
		<param r="10" g="82" b="0"/>
		<param r="0" g="88" b="79"/>
		<param r="11" g="90" b="222"/>
		<param r="8" g="108" b="339"/>
		<param r="8" g="131" b="462"/>
		<param r="69" g="190" b="599"/>
		<param r="262" g="279" b="818"/>
		<param r="0" g="209" b="787"/>
		<param r="0" g="230" b="903"/>
		<param r="92" g="238" b="7"/>
		<param r="92" g="238" b="90"/>
		<param r="76" g="242" b="225"/>
		<param r="67" g="248" b="340"/>
		<param r="84" g="252" b="457"/>
		<param r="41" g="265" b="565"/>
		<param r="41" g="279" b="682"/>
		<param r="10" g="287" b="800"/>
		<param r="7" g="305" b="921"/>
		<param r="176" g="358" b="37"/>
		<param r="128" g="362" b="109"/>
		<param r="158" g="364" b="231"/>
		<param r="131" g="368" b="345"/>
		<param r="151" g="372" b="455"/>
		<param r="162" g="378" b="568"/>
		<param r="137" g="384" b="684"/>
		<param r="135" g="395" b="802"/>
		<param r="122" g="403" b="922"/>
		<param r="251" g="484" b="89"/>
		<param r="249" g="484" b="137"/>
		<param r="250" g="485" b="246"/>
		<param r="240" g="488" b="351"/>
		<param r="244" g="491" b="460"/>
		<param r="233" g="495" b="572"/>
		<param r="235" g="501" b="687"/>
		<param r="223" g="507" b="804"/>
		<param r="224" g="516" b="924"/>
		<param r="309" g="603" b="119"/>
		<param r="309" g="604" b="167"/>
		<param r="305" g="604" b="259"/>
		<param r="303" g="606" b="360"/>
		<param r="302" g="609" b="468"/>
		<param r="298" g="612" b="577"/>
		<param r="299" g="616" b="692"/>
		<param r="291" g="623" b="808"/>
		<param r="290" g="628" b="927"/>
		<param r="381" g="731" b="167"/>
		<param r="381" g="731" b="204"/>
		<param r="302" g="729" b="281"/>
		<param r="378" g="733" b="372"/>
		<param r="329" g="736" b="477"/>
		<param r="375" g="738" b="584"/>
		<param r="310" g="743" b="698"/>
		<param r="365" g="747" b="812"/>
		<param r="349" g="752" b="932"/>
		<param r="447" g="857" b="165"/>
		<param r="448" g="857" b="202"/>
		<param r="447" g="856" b="295"/>
		<param r="446" g="858" b="385"/>
		<param r="444" g="859" b="487"/>
		<param r="442" g="862" b="591"/>
		<param r="440" g="865" b="705"/>
		<param r="437" g="868" b="818"/>
		<param r="432" g="872" b="937"/>
		<param r="509" g="977" b="238"/>
		<param r="508" g="977" b="256"/>
		<param r="508" g="978" b="315"/>
		<param r="507" g="979" b="401"/>
		<param r="506" g="980" b="498"/>
		<param r="503" g="982" b="600"/>
		<param r="503" g="984" b="712"/>
		<param r="498" g="988" b="825"/>
		<param r="496" g="990" b="942"/>
		<param r="70" g="6" b="0"/>
		<param r="47" g="1" b="69"/>
		<param r="73" g="2" b="222"/>
		<param r="70" g="27" b="339"/>
		<param r="51" g="72" b="451"/>
		<param r="34" g="98" b="565"/>
		<param r="26" g="128" b="681"/>
		<param r="12" g="166" b="799"/>
		<param r="1" g="204" b="920"/>
		<param r="72" g="80" b="0"/>
		<param r="80" g="86" b="74"/>
		<param r="87" g="98" b="222"/>
		<param r="91" g="113" b="339"/>
		<param r="63" g="131" b="451"/>
		<param r="55" g="160" b="565"/>
		<param r="49" g="178" b="681"/>
		<param r="29" g="209" b="799"/>
		<param r="13" g="229" b="920"/>
		<param r="142" g="239" b="8"/>
		<param r="139" g="240" b="90"/>
		<param r="126" g="243" b="225"/>
		<param r="134" g="246" b="340"/>
		<param r="105" g="255" b="451"/>
		<param r="106" g="265" b="565"/>
		<param r="106" g="276" b="685"/>
		<param r="71" g="289" b="800"/>
		<param r="73" g="306" b="920"/>
		<param r="208" g="362" b="44"/>
		<param r="206" g="363" b="110"/>
		<param r="197" g="363" b="232"/>
		<param r="183" g="372" b="345"/>
		<param r="125" g="373" b="460"/>
		<param r="173" g="379" b="568"/>
		<param r="175" g="386" b="687"/>
		<param r="189" g="394" b="803"/>
		<param r="171" g="404" b="922"/>
		<param r="274" g="484" b="90"/>
		<param r="272" g="485" b="137"/>
		<param r="272" g="486" b="246"/>
		<param r="262" g="488" b="351"/>
		<param r="266" g="491" b="461"/>
		<param r="253" g="496" b="572"/>
		<param r="256" g="502" b="687"/>
		<param r="241" g="508" b="804"/>
		<param r="244" g="516" b="924"/>
		<param r="326" g="604" b="119"/>
		<param r="325" g="604" b="167"/>
		<param r="321" g="605" b="259"/>
		<param r="320" g="607" b="360"/>
		<param r="318" g="609" b="468"/>
		<param r="315" g="613" b="577"/>
		<param r="314" g="617" b="692"/>
		<param r="308" g="624" b="808"/>
		<param r="308" g="629" b="927"/>
		<param r="394" g="732" b="167"/>
		<param r="394" g="732" b="204"/>
		<param r="390" g="733" b="277"/>
		<param r="390" g="734" b="372"/>
		<param r="365" g="736" b="477"/>
		<param r="388" g="739" b="584"/>
		<param r="348" g="744" b="698"/>
		<param r="380" g="747" b="812"/>
		<param r="366" g="753" b="932"/>
		<param r="459" g="855" b="209"/>
		<param r="459" g="856" b="225"/>
		<param r="456" g="856" b="295"/>
		<param r="456" g="858" b="385"/>
		<param r="455" g="859" b="487"/>
		<param r="452" g="862" b="591"/>
		<param r="451" g="865" b="705"/>
		<param r="447" g="869" b="818"/>
		<param r="443" g="872" b="937"/>
		<param r="518" g="977" b="238"/>
		<param r="517" g="977" b="256"/>
		<param r="517" g="978" b="316"/>
		<param r="516" g="979" b="401"/>
		<param r="515" g="980" b="498"/>
		<param r="513" g="982" b="600"/>
		<param r="512" g="985" b="712"/>
		<param r="507" g="988" b="825"/>
		<param r="505" g="990" b="942"/>
		<param r="238" g="18" b="0"/>
		<param r="229" g="28" b="72"/>
		<param r="228" g="39" b="222"/>
		<param r="216" g="55" b="339"/>
		<param r="219" g="77" b="451"/>
		<param r="213" g="105" b="565"/>
		<param r="211" g="135" b="681"/>
		<param r="208" g="174" b="799"/>
		<param r="199" g="208" b="919"/>
		<param r="237" g="89" b="0"/>
		<param r="232" g="103" b="77"/>
		<param r="232" g="107" b="223"/>
		<param r="222" g="125" b="339"/>
		<param r="225" g="135" b="451"/>
		<param r="219" g="163" b="565"/>
		<param r="218" g="186" b="681"/>
		<param r="212" g="214" b="799"/>
		<param r="203" g="229" b="919"/>
		<param r="260" g="243" b="11"/>
		<param r="256" g="245" b="93"/>
		<param r="237" g="247" b="224"/>
		<param r="244" g="254" b="341"/>
		<param r="250" g="261" b="452"/>
		<param r="235" g="269" b="565"/>
		<param r="237" g="281" b="682"/>
		<param r="226" g="290" b="800"/>
		<param r="224" g="308" b="920"/>
		<param r="286" g="364" b="48"/>
		<param r="285" g="364" b="113"/>
		<param r="281" g="365" b="234"/>
		<param r="278" g="369" b="345"/>
		<param r="276" g="372" b="455"/>
		<param r="272" g="380" b="568"/>
		<param r="273" g="385" b="684"/>
		<param r="263" g="397" b="802"/>
		<param r="260" g="405" b="922"/>
		<param r="331" g="485" b="92"/>
		<param r="331" g="485" b="139"/>
		<param r="326" g="486" b="243"/>
		<param r="326" g="489" b="352"/>
		<param r="314" g="494" b="461"/>
		<param r="319" g="498" b="572"/>
		<param r="291" g="505" b="688"/>
		<param r="306" g="511" b="804"/>
		<param r="312" g="519" b="924"/>
		<param r="381" g="606" b="121"/>
		<param r="382" g="606" b="168"/>
		<param r="376" g="607" b="260"/>
		<param r="377" g="608" b="360"/>
		<param r="372" g="611" b="468"/>
		<param r="374" g="614" b="577"/>
		<param r="367" g="619" b="692"/>
		<param r="366" g="625" b="808"/>
		<param r="360" g="631" b="927"/>
		<param r="435" g="733" b="169"/>
		<param r="435" g="733" b="205"/>
		<param r="432" g="734" b="278"/>
		<param r="431" g="735" b="373"/>
		<param r="430" g="737" b="477"/>
		<param r="428" g="740" b="584"/>
		<param r="426" g="744" b="698"/>
		<param r="424" g="748" b="813"/>
		<param r="421" g="753" b="932"/>
		<param r="492" g="856" b="210"/>
		<param r="491" g="856" b="230"/>
		<param r="490" g="857" b="296"/>
		<param r="489" g="858" b="385"/>
		<param r="489" g="860" b="488"/>
		<param r="485" g="863" b="591"/>
		<param r="486" g="865" b="705"/>
		<param r="481" g="870" b="818"/>
		<param r="479" g="873" b="937"/>
		<param r="550" g="978" b="239"/>
		<param r="550" g="978" b="257"/>
		<param r="549" g="979" b="316"/>
		<param r="549" g="980" b="401"/>
		<param r="546" g="981" b="498"/>
		<param r="545" g="983" b="600"/>
		<param r="543" g="986" b="712"/>
		<param r="539" g="989" b="825"/>
		<param r="538" g="991" b="942"/>
		<param r="344" g="24" b="0"/>
		<param r="350" g="49" b="79"/>
		<param r="345" g="61" b="223"/>
		<param r="347" g="79" b="340"/>
		<param r="337" g="107" b="451"/>
		<param r="339" g="135" b="565"/>
		<param r="330" g="158" b="681"/>
		<param r="324" g="192" b="799"/>
		<param r="324" g="215" b="919"/>
		<param r="355" g="122" b="1"/>
		<param r="353" g="126" b="82"/>
		<param r="348" g="140" b="216"/>
		<param r="351" g="149" b="340"/>
		<param r="340" g="160" b="451"/>
		<param r="343" g="178" b="565"/>
		<param r="335" g="201" b="681"/>
		<param r="328" g="221" b="799"/>
		<param r="327" g="239" b="919"/>
		<param r="365" g="247" b="19"/>
		<param r="363" g="248" b="98"/>
		<param r="359" g="251" b="228"/>
		<param r="360" g="255" b="342"/>
		<param r="351" g="263" b="452"/>
		<param r="357" g="272" b="566"/>
		<param r="353" g="279" b="688"/>
		<param r="341" g="297" b="800"/>
		<param r="343" g="308" b="922"/>
		<param r="391" g="369" b="53"/>
		<param r="390" g="370" b="116"/>
		<param r="384" g="372" b="232"/>
		<param r="376" g="374" b="346"/>
		<param r="379" g="380" b="456"/>
		<param r="381" g="385" b="568"/>
		<param r="373" g="392" b="684"/>
		<param r="373" g="401" b="802"/>
		<param r="366" g="410" b="922"/>
		<param r="415" g="489" b="96"/>
		<param r="415" g="489" b="142"/>
		<param r="413" g="490" b="248"/>
		<param r="410" g="493" b="353"/>
		<param r="406" g="495" b="460"/>
		<param r="408" g="500" b="572"/>
		<param r="400" g="504" b="687"/>
		<param r="405" g="512" b="804"/>
		<param r="388" g="522" b="925"/>
		<param r="456" g="608" b="125"/>
		<param r="456" g="608" b="171"/>
		<param r="455" g="608" b="261"/>
		<param r="452" g="611" b="361"/>
		<param r="453" g="613" b="469"/>
		<param r="449" g="617" b="578"/>
		<param r="449" g="622" b="693"/>
		<param r="446" g="628" b="808"/>
		<param r="442" g="634" b="928"/>
		<param r="503" g="735" b="172"/>
		<param r="503" g="735" b="207"/>
		<param r="502" g="736" b="279"/>
		<param r="499" g="738" b="374"/>
		<param r="499" g="739" b="478"/>
		<param r="495" g="743" b="585"/>
		<param r="496" g="746" b="698"/>
		<param r="488" g="751" b="813"/>
		<param r="488" g="755" b="932"/>
		<param r="548" g="858" b="212"/>
		<param r="547" g="858" b="232"/>
		<param r="546" g="859" b="297"/>
		<param r="546" g="860" b="386"/>
		<param r="544" g="862" b="488"/>
		<param r="543" g="864" b="592"/>
		<param r="542" g="867" b="705"/>
		<param r="538" g="871" b="818"/>
		<param r="538" g="874" b="937"/>
		<param r="600" g="980" b="221"/>
		<param r="600" g="980" b="240"/>
		<param r="601" g="980" b="317"/>
		<param r="601" g="982" b="402"/>
		<param r="597" g="983" b="498"/>
		<param r="599" g="985" b="601"/>
		<param r="574" g="987" b="713"/>
		<param r="594" g="990" b="825"/>
		<param r="572" g="993" b="943"/>
		<param r="468" g="84" b="8"/>
		<param r="466" g="87" b="89"/>
		<param r="464" g="93" b="226"/>
		<param r="459" g="108" b="341"/>
		<param r="463" g="123" b="452"/>
		<param r="456" g="152" b="566"/>
		<param r="458" g="176" b="682"/>
		<param r="451" g="210" b="799"/>
		<param r="449" g="230" b="919"/>
		<param r="470" g="138" b="14"/>
		<param r="468" g="141" b="92"/>
		<param r="467" g="146" b="227"/>
		<param r="462" g="161" b="341"/>
		<param r="465" g="174" b="452"/>
		<param r="459" g="199" b="566"/>
		<param r="461" g="216" b="682"/>
		<param r="453" g="235" b="799"/>
		<param r="451" g="253" b="920"/>
		<param r="480" g="263" b="36"/>
		<param r="478" g="264" b="106"/>
		<param r="474" g="268" b="226"/>
		<param r="472" g="272" b="343"/>
		<param r="474" g="278" b="453"/>
		<param r="467" g="285" b="567"/>
		<param r="470" g="295" b="683"/>
		<param r="461" g="306" b="800"/>
		<param r="461" g="320" b="921"/>
		<param r="494" g="373" b="64"/>
		<param r="492" g="374" b="123"/>
		<param r="491" g="375" b="239"/>
		<param r="488" g="379" b="348"/>
		<param r="489" g="382" b="457"/>
		<param r="485" g="390" b="569"/>
		<param r="487" g="395" b="685"/>
		<param r="480" g="407" b="802"/>
		<param r="480" g="416" b="922"/>
		<param r="520" g="494" b="103"/>
		<param r="519" g="495" b="148"/>
		<param r="515" g="497" b="239"/>
		<param r="515" g="498" b="354"/>
		<param r="509" g="502" b="462"/>
		<param r="512" g="507" b="573"/>
		<param r="512" g="513" b="688"/>
		<param r="504" g="519" b="805"/>
		<param r="506" g="526" b="925"/>
		<param r="547" g="611" b="131"/>
		<param r="547" g="612" b="176"/>
		<param r="544" g="612" b="263"/>
		<param r="544" g="614" b="363"/>
		<param r="542" g="617" b="470"/>
		<param r="541" g="621" b="579"/>
		<param r="539" g="625" b="693"/>
		<param r="536" g="632" b="809"/>
		<param r="536" g="637" b="928"/>
		<param r="584" g="738" b="177"/>
		<param r="584" g="738" b="209"/>
		<param r="581" g="739" b="281"/>
		<param r="583" g="740" b="375"/>
		<param r="579" g="743" b="479"/>
		<param r="581" g="745" b="585"/>
		<param r="569" g="750" b="699"/>
		<param r="575" g="754" b="813"/>
		<param r="565" g="759" b="932"/>
		<param r="626" g="861" b="216"/>
		<param r="625" g="862" b="237"/>
		<param r="622" g="862" b="299"/>
		<param r="623" g="863" b="387"/>
		<param r="621" g="865" b="489"/>
		<param r="620" g="868" b="593"/>
		<param r="618" g="871" b="706"/>
		<param r="618" g="874" b="819"/>
		<param r="609" g="877" b="936"/>
		<param r="669" g="982" b="242"/>
		<param r="668" g="982" b="260"/>
		<param r="667" g="983" b="319"/>
		<param r="668" g="984" b="403"/>
		<param r="666" g="985" b="500"/>
		<param r="665" g="987" b="602"/>
		<param r="663" g="989" b="713"/>
		<param r="662" g="992" b="826"/>
		<param r="659" g="995" b="943"/>
		<param r="583" g="120" b="22"/>
		<param r="581" g="125" b="99"/>
		<param r="579" g="132" b="229"/>
		<param r="578" g="149" b="342"/>
		<param r="576" g="169" b="453"/>
		<param r="578" g="187" b="566"/>
		<param r="573" g="208" b="682"/>
		<param r="572" g="224" b="800"/>
		<param r="568" g="242" b="920"/>
		<param r="585" g="180" b="29"/>
		<param r="583" g="182" b="101"/>
		<param r="581" g="186" b="230"/>
		<param r="580" g="195" b="342"/>
		<param r="578" g="207" b="453"/>
		<param r="579" g="217" b="567"/>
		<param r="574" g="232" b="683"/>
		<param r="574" g="245" b="800"/>
		<param r="570" g="263" b="920"/>
		<param r="590" g="269" b="44"/>
		<param r="588" g="270" b="115"/>
		<param r="587" g="272" b="233"/>
		<param r="586" g="277" b="345"/>
		<param r="584" g="283" b="454"/>
		<param r="585" g="292" b="568"/>
		<param r="580" g="300" b="683"/>
		<param r="581" g="315" b="801"/>
		<param r="577" g="331" b="921"/>
		<param r="605" g="386" b="73"/>
		<param r="604" g="386" b="129"/>
		<param r="601" g="382" b="242"/>
		<param r="603" g="398" b="350"/>
		<param r="598" g="395" b="458"/>
		<param r="598" g="400" b="570"/>
		<param r="595" g="407" b="686"/>
		<param r="597" g="415" b="803"/>
		<param r="590" g="425" b="923"/>
		<param r="619" g="500" b="111"/>
		<param r="619" g="500" b="154"/>
		<param r="617" g="501" b="254"/>
		<param r="616" g="503" b="356"/>
		<param r="615" g="507" b="464"/>
		<param r="614" g="511" b="574"/>
		<param r="611" g="514" b="688"/>
		<param r="613" g="522" b="805"/>
		<param r="609" g="533" b="926"/>
		<param r="648" g="618" b="137"/>
		<param r="648" g="618" b="182"/>
		<param r="646" g="619" b="266"/>
		<param r="645" g="621" b="364"/>
		<param r="644" g="624" b="471"/>
		<param r="643" g="628" b="579"/>
		<param r="642" g="633" b="694"/>
		<param r="641" g="638" b="809"/>
		<param r="637" g="644" b="929"/>
		<param r="678" g="742" b="183"/>
		<param r="677" g="743" b="214"/>
		<param r="676" g="743" b="284"/>
		<param r="675" g="745" b="377"/>
		<param r="675" g="747" b="480"/>
		<param r="672" g="750" b="586"/>
		<param r="672" g="753" b="700"/>
		<param r="669" g="758" b="814"/>
		<param r="667" g="762" b="933"/>
		<param r="713" g="864" b="218"/>
		<param r="712" g="865" b="237"/>
		<param r="712" g="865" b="302"/>
		<param r="711" g="867" b="389"/>
		<param r="711" g="868" b="491"/>
		<param r="709" g="871" b="594"/>
		<param r="710" g="874" b="707"/>
		<param r="706" g="878" b="819"/>
		<param r="705" g="881" b="938"/>
		<param r="751" g="985" b="245"/>
		<param r="751" g="985" b="263"/>
		<param r="751" g="986" b="321"/>
		<param r="751" g="987" b="405"/>
		<param r="749" g="988" b="501"/>
		<param r="748" g="990" b="603"/>
		<param r="747" g="993" b="714"/>
		<param r="744" g="996" b="826"/>
		<param r="744" g="998" b="944"/>
		<param r="700" g="167" b="44"/>
		<param r="699" g="169" b="111"/>
		<param r="698" g="175" b="234"/>
		<param r="696" g="188" b="344"/>
		<param r="696" g="203" b="455"/>
		<param r="694" g="216" b="567"/>
		<param r="695" g="229" b="683"/>
		<param r="690" g="246" b="800"/>
		<param r="689" g="263" b="921"/>
		<param r="702" g="210" b="50"/>
		<param r="701" g="211" b="113"/>
		<param r="700" g="214" b="235"/>
		<param r="697" g="220" b="345"/>
		<param r="698" g="228" b="455"/>
		<param r="695" g="239" b="568"/>
		<param r="696" g="252" b="684"/>
		<param r="691" g="268" b="801"/>
		<param r="691" g="285" b="921"/>
		<param r="707" g="288" b="69"/>
		<param r="706" g="293" b="126"/>
		<param r="705" g="296" b="239"/>
		<param r="703" g="300" b="348"/>
		<param r="703" g="305" b="457"/>
		<param r="701" g="312" b="569"/>
		<param r="702" g="321" b="685"/>
		<param r="697" g="332" b="802"/>
		<param r="697" g="344" b="922"/>
		<param r="718" g="394" b="87"/>
		<param r="717" g="394" b="139"/>
		<param r="716" g="395" b="246"/>
		<param r="714" g="399" b="352"/>
		<param r="714" g="403" b="460"/>
		<param r="712" g="410" b="572"/>
		<param r="713" g="416" b="687"/>
		<param r="708" g="426" b="804"/>
		<param r="709" g="435" b="923"/>
		<param r="734" g="510" b="122"/>
		<param r="733" g="510" b="163"/>
		<param r="729" g="513" b="242"/>
		<param r="731" g="514" b="359"/>
		<param r="730" g="517" b="466"/>
		<param r="729" g="522" b="575"/>
		<param r="728" g="527" b="690"/>
		<param r="724" g="533" b="806"/>
		<param r="726" g="540" b="926"/>
		<param r="753" g="624" b="148"/>
		<param r="753" g="624" b="191"/>
		<param r="751" g="625" b="270"/>
		<param r="751" g="627" b="367"/>
		<param r="750" g="630" b="473"/>
		<param r="749" g="633" b="581"/>
		<param r="748" g="638" b="695"/>
		<param r="746" g="644" b="810"/>
		<param r="745" g="649" b="929"/>
		<param r="779" g="748" b="191"/>
		<param r="779" g="748" b="217"/>
		<param r="776" g="750" b="272"/>
		<param r="778" g="750" b="379"/>
		<param r="776" g="753" b="482"/>
		<param r="777" g="756" b="588"/>
		<param r="774" g="760" b="701"/>
		<param r="773" g="764" b="815"/>
		<param r="760" g="768" b="933"/>
		<param r="807" g="869" b="221"/>
		<param r="806" g="869" b="240"/>
		<param r="805" g="870" b="304"/>
		<param r="806" g="871" b="392"/>
		<param r="804" g="873" b="492"/>
		<param r="805" g="875" b="595"/>
		<param r="802" g="878" b="708"/>
		<param r="802" g="882" b="820"/>
		<param r="799" g="885" b="939"/>
		<param r="839" g="989" b="249"/>
		<param r="839" g="989" b="266"/>
		<param r="838" g="990" b="323"/>
		<param r="839" g="990" b="407"/>
		<param r="837" g="992" b="502"/>
		<param r="838" g="994" b="604"/>
		<param r="835" g="997" b="715"/>
		<param r="836" g="999" b="827"/>
		<param r="833" g="1002" b="944"/>
		<param r="815" g="213" b="65"/>
		<param r="814" g="213" b="122"/>
		<param r="813" g="216" b="239"/>
		<param r="812" g="221" b="347"/>
		<param r="811" g="228" b="457"/>
		<param r="811" g="237" b="569"/>
		<param r="809" g="250" b="685"/>
		<param r="810" g="261" b="802"/>
		<param r="806" g="278" b="922"/>
		<param r="816" g="233" b="71"/>
		<param r="815" g="234" b="126"/>
		<param r="814" g="237" b="241"/>
		<param r="813" g="241" b="348"/>
		<param r="812" g="249" b="458"/>
		<param r="812" g="257" b="569"/>
		<param r="810" g="269" b="685"/>
		<param r="811" g="280" b="802"/>
		<param r="808" g="297" b="922"/>
		<param r="820" g="302" b="88"/>
		<param r="819" g="302" b="138"/>
		<param r="818" g="305" b="244"/>
		<param r="817" g="309" b="351"/>
		<param r="817" g="313" b="458"/>
		<param r="816" g="323" b="571"/>
		<param r="815" g="330" b="686"/>
		<param r="816" g="344" b="803"/>
		<param r="811" g="353" b="923"/>
		<param r="830" g="410" b="98"/>
		<param r="830" g="410" b="146"/>
		<param r="828" g="412" b="251"/>
		<param r="827" g="416" b="354"/>
		<param r="827" g="420" b="463"/>
		<param r="826" g="425" b="573"/>
		<param r="825" g="431" b="688"/>
		<param r="825" g="438" b="804"/>
		<param r="821" g="447" b="924"/>
		<param r="841" g="517" b="133"/>
		<param r="841" g="517" b="172"/>
		<param r="840" g="518" b="262"/>
		<param r="839" g="520" b="362"/>
		<param r="839" g="523" b="468"/>
		<param r="838" g="528" b="577"/>
		<param r="837" g="533" b="692"/>
		<param r="837" g="539" b="807"/>
		<param r="834" g="547" b="927"/>
		<param r="860" g="633" b="158"/>
		<param r="860" g="633" b="200"/>
		<param r="858" g="635" b="274"/>
		<param r="858" g="637" b="369"/>
		<param r="858" g="639" b="475"/>
		<param r="856" g="643" b="582"/>
		<param r="856" g="648" b="696"/>
		<param r="855" g="653" b="811"/>
		<param r="852" g="659" b="930"/>
		<param r="880" g="754" b="200"/>
		<param r="879" g="754" b="223"/>
		<param r="878" g="755" b="291"/>
		<param r="878" g="756" b="382"/>
		<param r="878" g="758" b="484"/>
		<param r="876" g="761" b="589"/>
		<param r="876" g="764" b="702"/>
		<param r="874" g="769" b="816"/>
		<param r="873" g="773" b="934"/>
		<param r="905" g="875" b="226"/>
		<param r="904" g="875" b="239"/>
		<param r="904" g="876" b="308"/>
		<param r="904" g="877" b="394"/>
		<param r="904" g="878" b="494"/>
		<param r="902" g="881" b="596"/>
		<param r="902" g="884" b="709"/>
		<param r="900" g="888" b="821"/>
		<param r="899" g="891" b="939"/>
		<param r="930" g="993" b="253"/>
		<param r="930" g="993" b="270"/>
		<param r="930" g="994" b="326"/>
		<param r="930" g="995" b="409"/>
		<param r="929" g="996" b="504"/>
		<param r="928" g="998" b="605"/>
		<param r="928" g="1000" b="716"/>
		<param r="926" g="1004" b="828"/>
		<param r="926" g="1006" b="945"/>
		<param r="927" g="240" b="88"/>
		<param r="927" g="240" b="138"/>
		<param r="926" g="243" b="246"/>
		<param r="925" g="248" b="350"/>
		<param r="925" g="255" b="458"/>
		<param r="924" g="265" b="570"/>
		<param r="923" g="237" b="686"/>
		<param r="921" g="291" b="802"/>
		<param r="922" g="307" b="922"/>
		<param r="928" g="261" b="93"/>
		<param r="928" g="261" b="140"/>
		<param r="927" g="264" b="244"/>
		<param r="926" g="269" b="351"/>
		<param r="925" g="234" b="460"/>
		<param r="925" g="286" b="571"/>
		<param r="925" g="281" b="686"/>
		<param r="922" g="310" b="803"/>
		<param r="923" g="323" b="922"/>
		<param r="932" g="330" b="104"/>
		<param r="931" g="330" b="151"/>
		<param r="931" g="332" b="249"/>
		<param r="930" g="336" b="354"/>
		<param r="930" g="340" b="461"/>
		<param r="929" g="348" b="572"/>
		<param r="928" g="355" b="687"/>
		<param r="926" g="366" b="804"/>
		<param r="927" g="377" b="923"/>
		<param r="939" g="422" b="115"/>
		<param r="939" g="423" b="160"/>
		<param r="938" g="424" b="257"/>
		<param r="937" g="427" b="357"/>
		<param r="937" g="431" b="465"/>
		<param r="936" g="436" b="575"/>
		<param r="936" g="443" b="690"/>
		<param r="934" g="451" b="805"/>
		<param r="934" g="460" b="925"/>
		<param r="950" g="531" b="146"/>
		<param r="950" g="531" b="183"/>
		<param r="949" g="532" b="266"/>
		<param r="948" g="535" b="365"/>
		<param r="948" g="538" b="470"/>
		<param r="947" g="542" b="579"/>
		<param r="946" g="547" b="693"/>
		<param r="945" g="552" b="808"/>
		<param r="945" g="559" b="927"/>
		<param r="964" g="641" b="172"/>
		<param r="963" g="641" b="208"/>
		<param r="962" g="642" b="279"/>
		<param r="962" g="643" b="373"/>
		<param r="961" g="646" b="477"/>
		<param r="961" g="650" b="584"/>
		<param r="960" g="654" b="698"/>
		<param r="959" g="660" b="812"/>
		<param r="958" g="665" b="931"/>
		<param r="982" g="762" b="208"/>
		<param r="980" g="762" b="224"/>
		<param r="980" g="763" b="294"/>
		<param r="981" g="764" b="385"/>
		<param r="979" g="767" b="485"/>
		<param r="980" g="770" b="591"/>
		<param r="978" g="774" b="703"/>
		<param r="978" g="778" b="817"/>
		<param r="976" g="782" b="935"/>
		<param r="1001" g="880" b="231"/>
		<param r="1000" g="880" b="249"/>
		<param r="1000" g="881" b="312"/>
		<param r="1001" g="882" b="397"/>
		<param r="999" g="884" b="496"/>
		<param r="999" g="886" b="598"/>
		<param r="997" g="889" b="710"/>
		<param r="997" g="892" b="822"/>
		<param r="996" g="896" b="940"/>
		<param r="1021" g="1000" b="254"/>
		<param r="1023" g="999" b="251"/>
		<param r="1022" g="1000" b="323"/>
		<param r="1022" g="1001" b="401"/>
		<param r="1021" g="1003" b="505"/>
		<param r="1021" g="1005" b="609"/>
		<param r="1022" g="1007" b="717"/>
		<param r="1022" g="1010" b="830"/>
		<param r="1020" g="1012" b="945"/>
	</reg_table>
</LUT_config>